store_kit/__init__.py
store_kit/http/__init__.py
store_kit/http/status.py
store_kit/py.typed
store_kit/utils/__init__.py
store_kit/utils/humps.py
django_store_kit-0.1.3.dist-info/LICENSE
django_store_kit-0.1.3.dist-info/METADATA
django_store_kit-0.1.3.dist-info/WHEEL
django_store_kit-0.1.3.dist-info/RECORD
