Metadata-Version: 2.1
Name: django-store-kit
Version: 0.1.3
Summary: Store kit is a package that provides common modules and utilities used for personal e-commerce projects.
License: MIT
Author: Daniel Kjellid
Author-email: daniel.kjellid@gmail.com
Requires-Python: >=3.11,<4.0
Classifier: License :: OSI Approved :: MIT License
Classifier: Programming Language :: Python :: 3
Classifier: Programming Language :: Python :: 3.11
Requires-Dist: django (>=4.1.7,<5.0.0)
